redfish_service_validator/RedfishLogo.py
redfish_service_validator/RedfishServiceValidator.py
redfish_service_validator/RedfishServiceValidatorGui.py
redfish_service_validator/__init__.py
redfish_service_validator/catalog.py
redfish_service_validator/config.py
redfish_service_validator/helper.py
redfish_service_validator/logger.py
redfish_service_validator/metadata.py
redfish_service_validator/schema_pack.py
redfish_service_validator/tohtml.py
redfish_service_validator/traverse.py
redfish_service_validator/validateRedfish.py
redfish_service_validator/validateResource.py
redfish_service_validator-2.5.1.dist-info/licenses/AUTHORS.md
redfish_service_validator-2.5.1.dist-info/licenses/LICENSE.md
redfish_service_validator-2.5.1.dist-info/METADATA
redfish_service_validator-2.5.1.dist-info/WHEEL
redfish_service_validator-2.5.1.dist-info/entry_points.txt
redfish_service_validator-2.5.1.dist-info/top_level.txt
redfish_service_validator-2.5.1.dist-info/RECORD
